genai_agents/AIAgent.py
genai_agents/MessageBroker.py
genai_agents/PQ.py
genai_agents/__init__.py
genai_agents/agentsInit.py
genai_agents/config/agentConfig.yaml
genai_agents/custom_tools/ProxyTool.py
genai_agents/custom_tools/__init__.py
genai_agents/custom_tools/custom_tool_db.py
genai_agents/mylogger.py
genai_agents/timerPool.py
genai_agents/tools/base.py
genai_agents/tools/functional_tools/__init__.py
genai_agents/tools/functional_tools/dalle_imagegenerator.py
genai_agents/tools/functional_tools/documentcompare_tool.py
genai_agents/tools/functional_tools/exaSearch_tool.py
genai_agents/tools/functional_tools/github_tool.py
genai_agents/tools/functional_tools/gmail_tool.py
genai_agents/tools/functional_tools/nasa_tool.py
genai_agents/tools/functional_tools/openweathermap_tool.py
genai_agents/tools/functional_tools/polygon_tool.py
genai_agents/tools/functional_tools/sql_tool.py
genai_agents/tools/functional_tools/xorbits_tool.py
genai_agents/tools/tools_db.py
genai_agents/tools/tools_utils.py
genai_agents/tools/websearch/__init__.py
genai_agents/tools/websearch/duckducksearch.py
genai_agents/tools/websearch/google.py
genai_agents/tools/websearch/google_finance_search.py
genai_agents/tools/websearch/google_serper_specific.py
genai_agents/tools/websearch/googlejobsearch.py
genai_agents/tools/websearch/googleserpersearch.py
genai_agents/tools/websearch/serper_intermediate.py
genai_agents/tools/websearch/wikipedia_tool.py
genai_agents/tools/websearch/yahoofinancenews.py
genai_agents/tools/websearch/youtubesearch.py
genai_agents/utils/extraction.py
genai_agents/utils/llmTasks.py
genai_agents/utils/yamlParse.py
genai_agents-0.1.3.dist-info/METADATA
genai_agents-0.1.3.dist-info/WHEEL
genai_agents-0.1.3.dist-info/RECORD
